secure_encryption/__init__.py
secure_encryption/crypto_service.py
secure_encryption-0.0.1.dist-info/METADATA
secure_encryption-0.0.1.dist-info/WHEEL
secure_encryption-0.0.1.dist-info/top_level.txt
secure_encryption-0.0.1.dist-info/RECORD
