Metadata-Version: 2.1
Name: secure-encryption
Version: 0.0.1
Summary: A simple and secure encryption service for Python.
Home-page: https://github.com/irfanul/secure-encryption-python
Author: Mohammed Irfanul Alam Tanveer
Author-email: irfanulalamtanvir@gmail.com
Classifier: Programming Language :: Python :: 3
Classifier: License :: OSI Approved :: MIT License
Classifier: Operating System :: OS Independent
Requires-Python: >=3.6
Requires-Dist: pycryptodome
